{"mean":{"confidence_interval":{"confidence_level":0.95,"lower_bound":53956478.8225,"upper_bound":58294274.9555},"point_estimate":56063335.16,"standard_error":1108162.735109713},"median":{"confidence_interval":{"confidence_level":0.95,"lower_bound":51077626.0,"upper_bound":60865702.0},"point_estimate":59216987.5,"standard_error":3226458.9357562927},"median_abs_dev":{"confidence_interval":{"confidence_level":0.95,"lower_bound":8716956.55279309,"upper_bound":15388375.11100173},"point_estimate":13261512.060061097,"standard_error":1775135.001311336},"slope":null,"std_dev":{"confidence_interval":{"confidence_level":0.95,"lower_bound":9637732.157442372,"upper_bound":12449345.808259187},"point_estimate":11166786.531285595,"standard_error":715332.5936314093}}